metaphora/__init__.py
metaphora-0.0.1.dist-info/LICENSE
metaphora-0.0.1.dist-info/METADATA
metaphora-0.0.1.dist-info/WHEEL
metaphora-0.0.1.dist-info/top_level.txt
metaphora-0.0.1.dist-info/RECORD
