Metadata-Version: 2.1
Name: metaphora
Version: 0.0.1
Summary: From Ancient Greek μεταφορά (metaphorá), from μεταφέρω (metaphérō, “I transfer, apply”), from μετά (metá, “with, across, after”) + φέρω (phérō, “I bear, carry”). 
Author-email: Alexander Fedotov <alex.fedotov@aol.com>
Project-URL: Homepage, https://github.com/alxfed/metaphora
Project-URL: Bug Tracker, https://github.com/alxfed/metaphora/issues
Classifier: Programming Language :: Python :: 3
Classifier: License :: OSI Approved :: MIT License
Classifier: Operating System :: OS Independent
Requires-Python: >=3.10
License-File: LICENSE
